ephysio/__init__.py
ephysio/kilosortIO.py
ephysio/kilosortio.py
ephysio/openEphysIO.py
ephysio/openephysio.py
ephysio/spikeGLXIO.py
ephysio/spikeglxio.py
ephysio/spikestats.py
ephysio/timeMachine.py
ephysio/timemachine.py
ephysio/vizio.py
ephysio/vizly.py
ephysio-1.0.13.dist-info/licenses/LICENSE
ephysio-1.0.13.dist-info/METADATA
ephysio-1.0.13.dist-info/WHEEL
ephysio-1.0.13.dist-info/top_level.txt
ephysio-1.0.13.dist-info/RECORD
