Metadata-Version: 2.4
Name: ephysio
Version: 1.0.13
Summary: Tools for reading ephys data
Author-email: Daniel Wagenaar <daw@caltech.edu>
License-File: LICENSE
Requires-Dist: numpy
Dynamic: license-file
